{
    "pagination": {
        "limit": 25,
        "offset": 0,
        "count": 25,
        "total": 10000
    },"data": [
        {
            "author": "Associated Press",
            "category": "general",
            "country": "us",
            "description": "Woman, 62, dies after being hit by glass from shattered cabin windows during a storm",
            "title": "U.S. passenger killed when big wave hits Antarctic cruise ship",
            "source": "torontosun",
            "url": "https://torontosun.com/news/world/u-s-passenger-killed-when-big-wave-hits-antarctic-cruise-ship",
            "image": null,
            "language": "en",
            "published_at": "2022-12-02T16:42:08Z"
        },
        {
            "author": "Shivaditya Ghoshal",
            "category": "sports",
            "country": "us",
            "description": "MrBeast has a very popular persona, and fans are always curious about him and his personal information. However, sometimes fans just ask really weird questions that can make someone wonder as well as make them laugh. And this was seen to get true when, a lot of times, fans asked random questions to streamers and&#8230;The post “Give You the F**King Plans to His House” &#8211; Political Streamer HasanAbi Hilariously Responds to a Fan’s Suspicious Question Regarding MrBeast’s Security Measures appeared first on EssentiallySports.",
            "title": "“Give You the F**King Plans to His House” – Political Streamer HasanAbi Hilariously Responds to a Fan’s Suspicious Question Regarding MrBeast’s Security Measures",
            "source": "Essentially Sports",
            "url": "https://www.essentiallysports.com/esports-news-give-you-the-fking-plans-to-his-house-political-streamer-hasan-abi-hilariously-responds-to-a-fans-suspicious-question-regarding-mrbeasts-security-measures/",
            "image": "https://image-cdn.essentiallysports.com/wp-content/uploads/mrbeast-1-23-560x315.jpg",
            "language": "en",
            "published_at": "2022-12-02T16:40:40Z"
        },
        {
            "author": null,
            "category": "general",
            "country": "us",
            "description": "A key electrical power plant in a Moscow-backed breakaway region of Moldova will not resume energy supplies to the rest of the country after officials failed to reach any agreements on Friday amid an acute energy crisis, authorities said",
            "title": "Talks with breakaway region fail to ease Moldova energy woes",
            "source": "lulegacy",
            "url": "https://www.marketbeat.com/articles/talks-with-breakaway-region-fail-to-ease-moldova-energy-woes-2022-12-02/",
            "image": null,
            "language": "en",
            "published_at": "2022-12-02T16:40:24Z"
        },
        {
            "author": "Steven Ellis, Daily Faceoff",
            "category": "sports",
            "country": "us",
            "description": "According to the Brandon Sun’s Perry Bergson in a story published Friday, four Brandon Wheat Kings players were able to help a man who was contemplating suicide earlier this week.",
            "title": "Four Brandon Wheat Kings players help save man’s life",
            "source": "Yardbarker",
            "url": "https://www.yardbarker.com/nhl/articles/four_brandon_wheat_kings_players_help_save_mans_life/s1_16958_38194614",
            "image": "http://www.yardbarker.com/media/1/e/1e65185f1eab87df9ff92c0817c596964cc0223b/thumb_16x9/four-brandon-wheat-kings-players-help-save-mans.jpg",
            "language": "en",
            "published_at": "2022-12-02T16:41:06Z"
        },
        {
            "author": "Reuters",
            "category": "general",
            "country": "us",
            "description": "* Brazil&#8217;s Lula mulls U.S. trip before inauguration * Brazil&#8217;s Lula needs $29 bln spending cap to meet promises * Peru Congress backs motion to start impeachment against Castillo Dec 2 (Reuters) &#8211; The latest in Latin American politics today: U.S. imposes sanctions on two Haitian politicians over drug trafficking WASHINGTON &#8211; The United States [&#8230;]",
            "title": "U.S. imposes sanctions on two Haitian politicians over drug trafficking",
            "source": "nationalpost",
            "url": "https://nationalpost.com/pmn/news-pmn/crime-pmn/u-s-imposes-sanctions-on-two-haitian-politicians-over-drug-trafficking-2",
            "image": null,
            "language": "en",
            "published_at": "2022-12-02T17:02:50Z"
        },
        {
            "author": "Reuters",
            "category": "general",
            "country": "us",
            "description": "* Idi Amin expelled 55,000 Ugandan Asians in 1972 * Thousands of abandoned properties seized by the state * Fifty years on, graft seen plaguing reclamation bids By Liam Taylor KAMPALA, Dec 2 (Thomson Reuters Foundation) &#8211; Amin Visram remembers the joy of his childhood in Uganda: games of marbles, badminton, the laughter of his [&#8230;]",
            "title": "Expelled Ugandan Asians fight for seized properties 50 years on",
            "source": "nationalpost",
            "url": "https://nationalpost.com/pmn/news-pmn/crime-pmn/expelled-ugandan-asians-fight-for-seized-properties-50-years-on",
            "image": null,
            "language": "en",
            "published_at": "2022-12-02T17:02:06Z"
        },
        {
            "author": "David Badash",
            "category": "general",
            "country": "us",
            "description": "Lachlan Murdoch, the executive chairman and CEO of Fox News&#8216; parent company, Fox Corporation, is set to be deposed next week in a $1.6 billion defamation lawsuit. Dominion Voting Systems, which manufactures voting machines, claims the eldest Murdoch son and his father, Rupert Murdoch, have responsibility in Fox News promoting pro-Trump false election fraud claims [&#8230;]The post Fox News Chief Lachlan Murdoch to Be Deposed in $1.6 Billion Dominion Defamation Case appeared first on The New Civil Rights Movement.",
            "title": "Fox News Chief Lachlan Murdoch to Be Deposed in $1.6 Billion Dominion Defamation Case",
            "source": "thenewcivilrightsmovement",
            "url": "https://www.thenewcivilrightsmovement.com/2022/12/fox-news-chief-lachlan-murdoch-to-be-deposed-in-1-6-billion-dominion-defamation-case/",
            "image": null,
            "language": "en",
            "published_at": "2022-12-02T17:06:22Z"
        },
        {
            "author": "Steven Ellis, Daily Faceoff",
            "category": "sports",
            "country": "us",
            "description": "In a report published on Friday morning, Hockey Canada said there were 512 acts of discrimination reported by officials in 2021-22 and another 415 alleged incidents that were “not witnessed” by an official.",
            "title": "Hockey Canada reports more than 900 documented or alleged incidents of on-ice discrimination in 2021-22",
            "source": "Yardbarker",
            "url": "https://www.yardbarker.com/nhl/articles/hockey_canada_reports_more_than_900_documented_or_alleged_incidents_of_on_ice_discrimination_in_2021_22/s1_16958_38194758",
            "image": "http://www.yardbarker.com/media/7/0/704c3458a40149cc483a37e61d648421842a050b/thumb_16x9/hockey-canada-reports-staggering-amount.jpg",
            "language": "en",
            "published_at": "2022-12-02T17:09:12Z"
        },
        {
            "author": null,
            "category": "general",
            "country": "us",
            "description": "James Michael Grimes, 28, was on the first day of a Thanksgiving cruise with 18 family members when he vanished. He says he wasnt drunk but admitted some drinks before doing an air guitar solo.",
            "title": "Carnival cruise man who went overboard 'wasn't drunk' but had day drinks before air guitar contest",
            "source": "dailymail",
            "url": "https://www.dailymail.co.uk/news/article-11495783/Carnival-cruise-man-went-overboard-wasnt-drunk-day-drinks-air-guitar-contest.html?ns_mchannel=rss&ito=1490&ns_campaign=1490",
            "image": "https://i.dailymail.co.uk/1s/2022/12/02/16/65180113-0-image-m-10_1669999903353.jpg",
            "language": "en",
            "published_at": "2022-12-02T17:02:39Z"
        },
        {
            "author": "Reuters",
            "category": "general",
            "country": "us",
            "description": "HOUSTON &#8212; Oil futures were little changed in choppy trading on Friday ahead of a meeting of the Organization of the Petroleum Exporting Countries and its allies (OPEC+) on Sunday and an EU ban on Russian crude on Monday. Brent crude futures were down 15 cents, or 0.2%, at $86.75 per barrel by 11:33 a.m. [&#8230;]",
            "title": "Oil steadies ahead of OPEC+ meeting, EU Russian oil ban",
            "source": "business",
            "url": "https://financialpost.com/pmn/business-pmn/oil-steadies-ahead-of-opec-meeting-eu-russian-oil-ban",
            "image": null,
            "language": "en",
            "published_at": "2022-12-02T17:04:12Z"
        },
        {
            "author": "Cameron Scheetz",
            "category": "general",
            "country": "us",
            "description": "From her latest role in sci-fi epic 'The Peripheral' to her very first role in 'Vampire Lesbians Of Sodom'—yes, really—Alexandra Billings looks back.",
            "title": "Alexandra Billings looks back on her legendary career and the one role she wants a “do-over” on",
            "source": "queerty",
            "url": "https://www.queerty.com/alexandra-billings-looks-back-legendary-career-one-role-wants-20221202?utm_source=rss&utm_medium=rss&utm_campaign=alexandra-billings-looks-back-legendary-career-one-role-wants",
            "image": null,
            "language": "en",
            "published_at": "2022-12-02T17:00:59Z"
        },
        {
            "author": "AP News",
            "category": "general",
            "country": "us",
            "description": "Chip Ganassi Racing has signed New Zealand driver Marcus Armstrong to join its IndyCar lineup next season",
            "title": "Ganassi adds another Kiwi in Armstrong to IndyCar lineup",
            "source": "mymotherlode",
            "url": "https://www.mymotherlode.com/sports/top-sports-general-news/2864228/ganassi-adds-another-kiwi-in-armstrong-to-indycar-lineup.html",
            "image": null,
            "language": "en",
            "published_at": "2022-12-02T17:05:11Z"
        },
        {
            "author": null,
            "category": "general",
            "country": "us",
            "description": "(marketscreener.com) United Airlines Inc is closeto reaching a deal to order dozens of Boeing's 787Dreamliner jets, the Wall Street Journal reported on Friday,citing people familiar with the matter. An agreement between United and Boeing could be completed assoon as this month, the report said. United said the company doesn't comment on...https://www.marketscreener.com/quote/stock/UNITED-AIRLINES-HOLDINGS-45899617/news/United-Airlines-nears-deal-for-dozens-of-Boeing-787-Dreamliner-jets-WSJ-42464877/?utm_medium=RSS&utm_content=20221202",
            "title": "United Airlines nears deal for dozens of Boeing 787 Dreamliner jets - WSJ",
            "source": "4-traders",
            "url": "https://www.marketscreener.com/quote/stock/UNITED-AIRLINES-HOLDINGS-45899617/news/United-Airlines-nears-deal-for-dozens-of-Boeing-787-Dreamliner-jets-WSJ-42464877/?utm_medium=RSS&utm_content=20221202",
            "image": null,
            "language": "en",
            "published_at": "2022-12-02T17:39:09Z"
        },
        {
            "author": null,
            "category": "general",
            "country": "us",
            "description": "(marketscreener.com) The CAC 40 Index is up 29.77 points or 0.44% this week to 6742.25 --Up for nine consecutive weeks --Up 979.91 points or 17.01% over the last nine weeks --Largest nine week point gain since the week ending June 5, 2020 --Largest nine week percentage gain since the week ending Dec. 31, 2020 --Longest winning...https://www.marketscreener.com/quote/index/CAC-40-4941/news/CAC-40-Index-Ends-the-Week-0-44-Higher-at-6742-25-Data-Talk-42464869/?utm_medium=RSS&utm_content=20221202",
            "title": "CAC 40 Index Ends the Week 0.44% Higher at 6742.25 -- Data Talk",
            "source": "4-traders",
            "url": "https://www.marketscreener.com/quote/index/CAC-40-4941/news/CAC-40-Index-Ends-the-Week-0-44-Higher-at-6742-25-Data-Talk-42464869/?utm_medium=RSS&utm_content=20221202",
            "image": null,
            "language": "en",
            "published_at": "2022-12-02T17:39:06Z"
        },
        {
            "author": null,
            "category": "general",
            "country": "us",
            "description": "(marketscreener.com) The DAX is down 11.99 points or 0.08% this week to 14529.39 --Largest one week point and percentage decline since the week ending Sept. 30, 2022 --Snaps an eight week winning streak --Today it is up 39.09 points or 0.27% --Up for three consecutive trading days --Up 173.94 points or 1.21% over the last three...https://www.marketscreener.com/quote/index/DAX-7395/news/DAX-Ends-the-Week-0-08-Lower-at-14529-39-Data-Talk-42464868/?utm_medium=RSS&utm_content=20221202",
            "title": "DAX Ends the Week 0.08% Lower at 14529.39 -- Data Talk",
            "source": "4-traders",
            "url": "https://www.marketscreener.com/quote/index/DAX-7395/news/DAX-Ends-the-Week-0-08-Lower-at-14529-39-Data-Talk-42464868/?utm_medium=RSS&utm_content=20221202",
            "image": null,
            "language": "en",
            "published_at": "2022-12-02T17:39:05Z"
        },
        {
            "author": null,
            "category": "business",
            "country": "us",
            "description": "iShares Morningstar Multi-Asset Income ETF declares monthly distribution of $0.0507",
            "title": "iShares Morningstar Multi-Asset Income ETF declares monthly distribution of $0.0507",
            "source": "Seeking Alpha",
            "url": "https://seekingalpha.com/news/3913628-ishares-morningstar-multi-asset-income-etf-declares-monthly-distribution-of-00507?utm_source=feed_news_all&utm_medium=referral",
            "image": null,
            "language": "en",
            "published_at": "2022-12-02T17:44:13Z"
        },
        {
            "author": "Petty Officer 1st Class Benjamin Lewis",
            "category": "general",
            "country": "us",
            "description": "221201-N-TR141-1047 SANTO DOMINGO, Dominican Republic (Dec. 1, 2022) Sailors assigned to U.S. Fleet Forces Band in Norfolk, Virginia, attached to hospital ship USNS Comfort (T-AH 20) for Continuing Promise 2022, perform for Mauricio Baez school students at the Mauricio Baez Cultural Center in Santo Domingo, Dominican Republic, Dec. 1, 2022. Comfort is deployed to U.S. 4th Fleet in support of Continuing Promise 2022, a humanitarian assistance and goodwill mission conducting direct medical care, expeditionary veterinary care, and subject matter expert exchanges with five partner nations in the...",
            "title": "U.S. Fleet Forces Band Performs at Mauricio Baez Cultural Center, Dominican Republic - CP22 [Image 2 of 9]",
            "source": "dvidshub",
            "url": "https://www.dvidshub.net/image/7537294/us-fleet-forces-band-performs-mauricio-baez-cultural-center-dominican-republic-cp22",
            "image": "https://cdn.dvidshub.net/media/thumbs/photos/2212/7537294/250x167_q75.jpg",
            "language": "en",
            "published_at": "2022-12-02T17:37:59Z"
        },
        {
            "author": "ABC6 News",
            "category": "general",
            "country": "us",
            "description": "WARWICK, R.I. (WLNE) &#8212; A convicted child rapist was in court Friday as prosecutors seek a review of his activity while on probation. In Kent County Superior Court, Richard Gardner signed documents waiving his Fourth Amendment right related to that review. Prosecutors agreed to continue the case to a later date. No further information was shared in court. Gardner was...",
            "title": "Convicted child rapist appears in court as prosecutors seek review of his activity",
            "source": "abc6",
            "url": "https://www.abc6.com/convicted-child-rapist-appears-in-court-as-prosecutors-seek-review-of-his-activity/",
            "image": null,
            "language": "en",
            "published_at": "2022-12-02T17:37:10Z"
        },
        {
            "author": "Sportsgrid-Staff",
            "category": "general",
            "country": "us",
            "description": "Another tight spread on a night of what should be many close games, as only a shot from deep separates the Wizards and Hornets in Charlotte.The post Washington Wizards vs. Charlotte Hornets Spread, Line, Odds, Predictions, Picks, and Betting Preview first appeared on SportsGrid.",
            "title": "Washington Wizards vs. Charlotte Hornets Spread, Line, Odds, Predictions, Picks, and Betting Preview",
            "source": "sportsgrid",
            "url": "https://www.sportsgrid.com/real-sports/nba/washington-wizards-vs-charlotte-hornets-spread-line-odds-predictions-picks-and-betting-preview/",
            "image": null,
            "language": "en",
            "published_at": "2022-12-02T17:38:01Z"
        },
        {
            "author": "The Associated Press",
            "category": "general",
            "country": "us",
            "description": "Twitter has suspended rapper Ye after he tweeted a picture of a swastika merged with the Star of David.",
            "title": "Twitter suspends rapper Ye over swastika post, Musk says",
            "source": "lvrj",
            "url": "https://www.reviewjournal.com/news/nation-and-world/twitter-suspends-rapper-ye-over-swastika-post-musk-says-2686750/",
            "image": null,
            "language": "en",
            "published_at": "2022-12-02T17:43:37Z"
        },
        {
            "author": "FRANKLIN BRICEÑO Associated Press",
            "category": "general",
            "country": "us",
            "description": "\"It has totally dried up,\" she said.",
            "title": "Lagoon dries up as drought grips Peru’s southern Andes",
            "source": "aurorasentinel",
            "url": "https://sentinelcolorado.com/uncategorized/lagoon-dries-up-as-drought-grips-perus-southern-andes/",
            "image": null,
            "language": "en",
            "published_at": "2022-12-02T17:41:07Z"
        },
        {
            "author": null,
            "category": "general",
            "country": "us",
            "description": "(marketscreener.com) &bull; &bull; &#894; &#894; &#894; Attachments Original Link Original Document Permalink Disclaimer Flow Traders NV published...https://www.marketscreener.com/quote/stock/FLOW-TRADERS-N-V-22852251/news/Flow-Traders-N-2022-EGM-Follow-up-Questions-42464889/?utm_medium=RSS&utm_content=20221202",
            "title": "Flow Traders N : 2022 EGM Follow-up Questions",
            "source": "4-traders",
            "url": "https://www.marketscreener.com/quote/stock/FLOW-TRADERS-N-V-22852251/news/Flow-Traders-N-2022-EGM-Follow-up-Questions-42464889/?utm_medium=RSS&utm_content=20221202",
            "image": null,
            "language": "en",
            "published_at": "2022-12-02T17:44:06Z"
        },
        {
            "author": "Drew Ascione",
            "category": "general",
            "country": "us",
            "description": "The motion to delay the Dec. 9 sentencing hearing of Defendant Paul Flores in the Kristin Smart murder trial to a later date has been approved. The post Paul Flores&#8217;s motion to delay Dec. 9 sentencing hearing approved and moved to March 10 2023. appeared first on News Channel 3-12.",
            "title": "Paul Flores’s motion to delay Dec. 9 sentencing hearing approved and moved to March 10 2023.",
            "source": "keyt",
            "url": "https://keyt.com/news/san-luis-obispo-county/2022/12/02/paul-floress-motion-to-delay-dec-9-sentencing-hearing-approved-and-moved-to-march-10-2023/",
            "image": null,
            "language": "en",
            "published_at": "2022-12-02T18:15:25Z"
        },
        {
            "author": null,
            "category": "general",
            "country": "us",
            "description": "WASHINGTON NAVY YARD – The Naval War College Museum, located in Newport, Rhode Island, will unveil its latest exhibit “Winds of Change: USS Constellation and the Dawn of the Modern Navy,” Dec. 5, with a reception in its gallery from 3-6 p.m.",
            "title": "USS Constellation Exhibit Set to Open at NWC",
            "source": "dvidshub",
            "url": "https://www.dvidshub.net/news/434385/uss-constellation-exhibit-set-open-nwc",
            "image": "https://cdn.dvidshub.net/media/thumbs/photos/1311/1059193/250x196_q75.jpg",
            "language": "en",
            "published_at": "2022-12-02T18:12:07Z"
        },
        {
            "author": "Nina Braca",
            "category": "general",
            "country": "us",
            "description": "AMC Star Norman Reedus says his series will have a completely different tone.",
            "title": "Norman Reedus Says ‘The Walking Dead: Daryl Dixon’ Is A ‘Fresh Start’ For Fans: ‘It’s F**king Great’",
            "source": "hitfix",
            "url": "https://uproxx.com/tv/norman-reedus-spinoff-daryl-dixon/",
            "image": null,
            "language": "en",
            "published_at": "2022-12-02T18:18:12Z"
        }    
    ]
}
